{
  "id": "edit-pdf-in-word",
  "title": "<p>אפשר לערוך PDF בוורד?</p><p>מסתבר שכן.</p>",
  "excerpt": "<p>שאלה שאני שומע הרבה.</p><p>והתשובה מפתיעה רוב האנשים.</p><p>כן. ופשוט.</p>",
  "body": "<p>לקוחות שואלים אותי הרבה:</p>\n\n<p>“איך אני עורך קובץ PDF?”<br>\nאו - “איך בכלל פותחים PDF בוורד?”</p>\n\n<p>וזאת שאלה מעולה.<br>\nכי זה באמת לא אינטואיטיבי.</p>\n\n<blockquote>\nהדרך הכי פשוטה לערוך PDF<br>\nהיא דרך תוכנה שכבר מותקנת אצלכם על המחשב - Microsoft Word.\n</blockquote>\n\n<h2>\n<svg width=\"20\" height=\"20\" viewBox=\"0 0 24 24\" fill=\"none\" stroke=\"var(--orange-deep)\" stroke-width=\"2.5\" stroke-linecap=\"round\" stroke-linejoin=\"round\"><path d=\"M12 20h9\"></path><path d=\"M16.5 3.5a2.121 2.121 0 0 1 3 3L7 19l-4 1 1-4L16.5 3.5z\"></path></svg>\nאיך פותחים PDF בוורד?\n</h2>\n\n<div>\n  <div>\n    <div>\n      <svg width=\"18\" height=\"18\" viewBox=\"0 0 24 24\" fill=\"none\" stroke=\"#fff\" stroke-width=\"2\" stroke-linecap=\"round\" stroke-linejoin=\"round\"><path d=\"M3 3l7.07 16.97 2.51-7.39 7.39-2.51L3 3z\"></path><path d=\"M13 13l6 6\"></path></svg>\n    </div>\n    מסמנים את קובץ ה״PDF ולוחצים כפתור ימני\n  </div>\n  <div>\n    <div>\n      <svg width=\"18\" height=\"18\" viewBox=\"0 0 24 24\" fill=\"none\" stroke=\"#fff\" stroke-width=\"2\" stroke-linecap=\"round\" stroke-linejoin=\"round\"><line x1=\"5\" y1=\"12\" x2=\"19\" y2=\"12\"></line><polyline points=\"12 5 19 12 12 19\"></polyline></svg>\n    </div>\n    בוחרים “פתח באמצעות” ואז “בחר אפליקציה אחרת”\n  </div>\n  <div>\n    <div>\n      <svg width=\"18\" height=\"18\" viewBox=\"0 0 24 24\" fill=\"none\" stroke=\"#fff\" stroke-width=\"2\" stroke-linecap=\"round\" stroke-linejoin=\"round\"><path d=\"M14 2H6a2 2 0 0 0-2 2v16a2 2 0 0 0 2 2h12a2 2 0 0 0 2-2V8z\"></path><polyline points=\"14 2 14 8 20 8\"></polyline><line x1=\"16\" y1=\"13\" x2=\"8\" y2=\"13\"></line><line x1=\"16\" y1=\"17\" x2=\"8\" y2=\"17\"></line><polyline points=\"10 9 9 9 8 9\"></polyline></svg>\n    </div>\n    בוחרים את Word ולוחצים “פעם אחת בלבד”\n  </div>\n  <div>\n    <div>\n      <svg width=\"18\" height=\"18\" viewBox=\"0 0 24 24\" fill=\"none\" stroke=\"#fff\" stroke-width=\"2\" stroke-linecap=\"round\" stroke-linejoin=\"round\"><path d=\"M22 11.08V12a10 10 0 1 1-5.93-9.14\"></path><polyline points=\"22 4 12 14.01 9 11.01\"></polyline></svg>\n    </div>\n    מאשרים המרה לעריכה - ומתחילים\n  </div>\n</div>\n\n<h2>\n<svg width=\"20\" height=\"20\" viewBox=\"0 0 24 24\" fill=\"none\" stroke=\"var(--orange-deep)\" stroke-width=\"2.5\" stroke-linecap=\"round\" stroke-linejoin=\"round\"><circle cx=\"12\" cy=\"12\" r=\"10\"></circle><line x1=\"12\" y1=\"8\" x2=\"12\" y2=\"12\"></line><line x1=\"12\" y1=\"16\" x2=\"12.01\" y2=\"16\"></line></svg>\nמה חשוב לדעת?\n</h2>\n\n<p>וורד לא מופיע ברשימה מיד,<br>\nכי הוא לא מוגדר כתוכנה שפותחת קבצי PDF באופן טבעי.<br>\nלכן צריך ללחוץ על “בחר אפליקציה אחרת” כדי למצוא אותו.</p>\n\n<p>אם הקובץ בעברית,<br>\nיכול להיות שהטקסט יוצג מיושר לשמאל.<br>\nבמקרה כזה: סמנו את כל הטקסט ולחצו על “יישור לימין”.</p>\n\n<p>זה לא תמיד מושלם כמו בקובץ PDF מקורי,<br>\nאבל זה נותן לכם אפשרות לערוך, לשנות,<br>\nולעבוד עם הטקסט - במקום רק להסתכל עליו.</p>\n\n<div class=\"post-insight\">\nלא צריך תוכנה מיוחדת כדי לערוך PDF.<br>\nוורד יודע לעשות את זה - רק צריך לדעת איפה ללחוץ.\n</div>",
  "date": "2024-10-23",
  "image": "https://media.omertai.net/edit-pdf-in-word.webp",
  "image_alt": "קובץ PDF שנפתח בתוך חלון Microsoft Word לעריכה, סמן עריכה מהבהב על שורת טקסט עם סרגל כלים של וורד למעלה",
  "seo_title": "אפשר לערוך PDF בוורד? מסתבר שכן | עומר טייכר",
  "seo_desc": "מדריך פשוט לפתיחה ועריכה של קובץ PDF דרך Microsoft Word."
}