{
  "title": "נא לא להפריע",
  "subtitle": "Windows",
  "totalSteps": 4,
  "slides": [
    {
      "index": 0,
      "type": "special",
      "specialType": "intro",
      "html": "<style>\n@keyframes fadeInDown{from{opacity:0;transform:translateY(-30px);}to{opacity:1;transform:translateY(0);}}\n@keyframes fadeInUp{from{opacity:0;transform:translateY(30px);}to{opacity:1;transform:translateY(0);}}\n@keyframes shimmer{0%{background-position:200% center;}100%{background-position:-200% center;}}\n.intro-wrap{display:flex;flex-direction:column;align-items:center;justify-content:flex-start;min-height:calc(100vh - 80px);background:#1a1a2e;text-align:center;padding:clamp(12px,2vh,20px) clamp(16px,3vw,40px) clamp(12px,2vh,20px);box-sizing:border-box;overflow-y:auto;}\n.intro-badge{background:linear-gradient(135deg,#3d5a80,#1e3050);color:white;padding:clamp(3px,0.5vh,5px) clamp(10px,1.5vw,16px);border-radius:50px;font-size:clamp(10px,1.2vw,12px);letter-spacing:2px;animation:fadeInDown .8s ease both;margin-bottom:clamp(6px,1vh,12px);}\n.intro-title{font-size:clamp(18px,3.5vw,46px);font-weight:900;color:white;line-height:1.15;animation:fadeInDown .9s ease .2s both;margin-bottom:clamp(4px,0.8vh,8px);}\n.intro-title span{background:linear-gradient(90deg,#f6a67e,#ff6b6b,#f6a67e);background-size:200% auto;-webkit-background-clip:text;-webkit-text-fill-color:transparent;animation:shimmer 3s linear infinite;}\n.intro-subtitle{font-size:clamp(11px,1.5vw,18px);color:#ffffffaa;animation:fadeInDown 1s ease .4s both;margin-bottom:clamp(2px,0.5vh,4px);line-height:1.5;}\n.intro-author{font-size:clamp(10px,1.1vw,13px);color:#ffffff66;animation:fadeInDown 1s ease .5s both;margin-bottom:clamp(10px,1.5vh,20px);}\n.intro-cards{display:flex;gap:clamp(8px,1vw,12px);flex-wrap:wrap;justify-content:center;animation:fadeInUp 1s ease .6s both;margin-bottom:clamp(10px,1.5vh,20px);}\n.intro-card{background:#ffffff12;border:1px solid #ffffff22;border-radius:clamp(10px,1vw,14px);padding:clamp(8px,1vh,12px) clamp(12px,1.5vw,18px);min-width:clamp(100px,12vw,130px);max-width:170px;}\n.intro-card .icon{font-size:24px;margin-bottom:clamp(2px,0.5vh,6px);}\n.intro-card .icon svg{width:clamp(20px,2.5vw,28px);height:clamp(20px,2.5vw,28px);}\n.intro-card .label{color:#ffffffcc;font-size:clamp(10px,1.1vw,12px);line-height:1.3;}\n.intro-btn{background:linear-gradient(135deg,#f6a67e,#e8834e);color:white;border:2px solid white;padding:clamp(8px,1.2vh,14px) clamp(24px,3vw,36px);border-radius:50px;font-size:clamp(12px,1.3vw,15px);font-weight:700;cursor:pointer;font-family:Rubik,sans-serif;box-shadow:0 6px 20px rgba(246,166,126,0.4);animation:fadeInUp 1s ease .8s both;}\n</style>\n<div class=\"intro-wrap\">\n<div class=\"intro-badge\">Windows</div>\n<div class=\"intro-title\">התראות קופצות כל הזמן?<br><span>\"נא לא להפריע\" עוצר הכל</span></div>\n<div class=\"intro-subtitle\">באמצע עבודה, מצגת, או שיחת וידאו.<br>קליק אחד ואין יותר הפרעות.<br>ההתראות ימתינו בשקט.</div>\n<div class=\"intro-author\">עומר טייכר · מדריך וטכנאי מחשבים</div>\n<div class=\"intro-cards\">\n<div class=\"intro-card\"><div class=\"icon\"><svg width=\"28\" height=\"28\" viewBox=\"0 0 24 24\" fill=\"none\" stroke=\"#f6a67e\" stroke-width=\"2\"><path d=\"M18 8A6 6 0 006 8c0 7-3 9-3 9h18s-3-2-3-9\"/><path d=\"M13.73 21a2 2 0 01-3.46 0\"/></svg></div><div class=\"label\">עוצר כל התראה מיד</div></div>\n<div class=\"intro-card\"><div class=\"icon\"><svg width=\"28\" height=\"28\" viewBox=\"0 0 24 24\" fill=\"none\" stroke=\"#f6a67e\" stroke-width=\"2\"><polygon points=\"13 2 3 14 12 14 11 22 21 10 12 10 13 2\"/></svg></div><div class=\"label\">קליק אחד להפעלה</div></div>\n<div class=\"intro-card\"><div class=\"icon\"><svg width=\"28\" height=\"28\" viewBox=\"0 0 24 24\" fill=\"none\" stroke=\"#f6a67e\" stroke-width=\"2\"><path d=\"M22 11.08V12a10 10 0 11-5.93-9.14\"/><polyline points=\"22 4 12 14.01 9 11.01\"/></svg></div><div class=\"label\">ההתראות נשמרות לאחר כך</div></div>\n</div>\n<button class=\"intro-btn\" onclick=\"nextSlide(1)\">&#9654;&nbsp;&nbsp;בואו נתחיל</button>\n</div>"
    },
    {
      "index": 1,
      "type": "special",
      "specialType": "howto-shared"
    },
    {
      "index": 2,
      "step": 1,
      "type": "view",
      "image": "DND-01.jpg",
      "text": "נמצאים בשולחן העבודה של Windows. מכאן נלמד להפעיל את מצב <span style=\"color:#f6a67e;\">נא לא להפריע</span> שמשתיק את כל ההתראות.<div style=\"text-align:center;margin-top:12px;\">לחצו על <span onclick=\"nextSlide()\" style=\"display:inline-flex;align-items:center;justify-content:center;width:36px;height:36px;background:linear-gradient(135deg,#1a2540,#3d5a80);border:2px solid white;border-radius:50%;cursor:pointer;vertical-align:middle;margin:0 6px;box-shadow:0 4px 12px rgba(26,37,64,0.5);\"><svg width=\"18\" height=\"18\" viewBox=\"0 0 24 24\" fill=\"none\" stroke=\"white\" stroke-width=\"3\" stroke-linecap=\"round\" stroke-linejoin=\"round\"><polyline points=\"9 18 15 12 9 6\"/></svg></span> כדי להמשיך בהדרכה.</div>",
      "textPos": {
        "left": "30%",
        "top": "30%"
      },
      "textWidth": "310px",
      "notes": [
        {
          "text": "",
          "left": "50%",
          "top": "50%"
        }
      ]
    },
    {
      "index": 3,
      "step": 2,
      "type": "click",
      "image": "DND-02.jpg",
      "text": "לחצו על <span style=\"color:#f6a67e;\">אזור ההתראות</span> (הפעמון בפינה השמאלית התחתונה, ליד השעון).",
      "textPos": {
        "left": "10.8915%",
        "top": "64.2029%"
      },
      "textWidth": "300px",
      "notes": [
        {
          "text": "",
          "left": "50%",
          "top": "50%"
        }
      ],
      "box": {
        "top": "90.6157%",
        "left": "0%",
        "right": "94.5701%",
        "bottom": "0%"
      }
    },
    {
      "index": 4,
      "step": 3,
      "type": "click",
      "image": "DND-03.jpg",
      "text": "נפתחה חלונית ההתראות. לחצו על <span style=\"color:#f6a67e;\">אל תפריע</span> בראש החלונית כדי להפעיל את המצב.",
      "textPos": {
        "left": "17.6988%",
        "top": "3.24774%"
      },
      "textWidth": "300px",
      "notes": [
        {
          "text": "",
          "left": "50%",
          "top": "50%"
        }
      ],
      "box": {
        "top": "1.54994%",
        "left": "8.02544%",
        "right": "85.3504%",
        "bottom": "89.2781%"
      }
    },
    {
      "index": 5,
      "step": 4,
      "type": "view",
      "image": "DND-04.jpg",
      "text": "<span style=\"color:#f6a67e;\">מצב 'אל תפריע' פעיל!</span> ההתראות לא ייעלמו. הן פשוט ימתינו בשקט עד שתהיו מוכנים לראות אותן. אפשר לכבות בכל רגע באותו מקום.",
      "textPos": {
        "left": "34.4185%",
        "top": "25%"
      },
      "textWidth": "320px",
      "notes": [
        {
          "text": "",
          "left": "50%",
          "top": "50%"
        }
      ]
    }
  ]
}
